moses/__init__.py
moses/admin.py
moses/apps.py
moses/authentication.py
moses/common/__init__.py
moses/common/error_codes.py
moses/common/exception_handlers.py
moses/common/exceptions.py
moses/common/renderers.py
moses/common/views.py
moses/conf.py
moses/constants/__init__.py
moses/constants/strings.py
moses/decorators.py
moses/enums.py
moses/migrations/0001_initial.py
moses/migrations/0002_remove_customuser_last_phone_number_confirmation_pins_sent_and_more.py
moses/migrations/__init__.py
moses/models.py
moses/serializers.py
moses/services/__init__.py
moses/services/credentials_confirmation.py
moses/services/mfa.py
moses/services/reset_password.py
moses/services/sms.py
moses/templates/admin/login.html
moses/urls.py
moses/validators.py
moses/views/__init__.py
moses/views/token_obtain_pair.py
moses/views/user.py
django_moses-0.12.13.dist-info/METADATA
django_moses-0.12.13.dist-info/WHEEL
django_moses-0.12.13.dist-info/licenses/LICENSE
django_moses-0.12.13.dist-info/RECORD
