Metadata-Version: 2.4
Name: django-moses
Version: 0.12.13
Summary: Advanced authentication with OTP and phone number verification
License-File: LICENSE
Author: Vassily Vorobyov
Author-email: l3acucm@gmail.com
Requires-Python: >=3.13,<4.0
Classifier: Programming Language :: Python :: 3
Classifier: Programming Language :: Python :: 3.13
Classifier: Programming Language :: Python :: 3.14
Requires-Dist: django (>=5.2.0,<6.0)
Requires-Dist: djangorestframework-simplejwt (>=5.5.0,<6.0.0)
Requires-Dist: djoser (>=2.3.1,<3.0.0)
Requires-Dist: pyotp (>=2.9.0,<3.0.0)
